{"__symbolic":"module","version":4,"metadata":{"KakaoMapsModule":{"__symbolic":"class","decorators":[{"__symbolic":"call","expression":{"__symbolic":"reference","module":"@angular/core","name":"NgModule","line":5,"character":1},"arguments":[{"imports":[{"__symbolic":"reference","module":"@angular/common","name":"CommonModule","line":7,"character":4}],"providers":[{"__symbolic":"reference","name":"KakaoMapsProvider"}],"exports":[{"__symbolic":"reference","name":"KakaoMapsComponent"}],"declarations":[{"__symbolic":"reference","name":"KakaoMapsComponent"}]}]}],"members":{}},"AbstractOverlay":{"__symbolic":"class","members":{"__ctor__":[{"__symbolic":"constructor"}],"draw":[{"__symbolic":"method"}],"onAdd":[{"__symbolic":"method"}],"onRemove":[{"__symbolic":"method"}],"setMap":[{"__symbolic":"method"}],"getMap":[{"__symbolic":"method"}],"getPanels":[{"__symbolic":"method"}],"getProjection":[{"__symbolic":"method"}]}},"Circle":{"__symbolic":"class","members":{"__ctor__":[{"__symbolic":"constructor","parameters":[{"__symbolic":"reference","name":"CircleClassOptions"}]}],"setMap":[{"__symbolic":"method"}],"getMap":[{"__symbolic":"method"}],"setZIndex":[{"__symbolic":"method"}],"getZIndex":[{"__symbolic":"method"}],"setOptions":[{"__symbolic":"method"}],"setPosition":[{"__symbolic":"method"}],"getPosition":[{"__symbolic":"method"}],"setRadius":[{"__symbolic":"method"}],"getRadius":[{"__symbolic":"method"}],"getBounds":[{"__symbolic":"method"}]}},"KakaoConstants":{"__symbolic":"class","members":{},"statics":{"MAP_API_END_POINT_PREFIX":"//dapi.kakao.com/v2/maps/sdk.js?appkey=","MAP_API_END_POINT_LIBRARY_OPTIONS":"&libraries=services,clusterer,drawing&autoload=false","APIKEY_ERROR":"KakaoMap is not initialized yet, call init(apiKey) first.","MAP_OBJECT_INIT_ERROR":"Map is not initialized yet."}},"OverlayType":{"__symbolic":"class","members":{},"statics":{"MARKER":null,"RECTANGLE":null,"CIRCLE":null,"ELLIPSE":null,"POLYLINE":null,"ARROW":null,"POLYGON":null}},"Status":{"__symbolic":"class","members":{},"statics":{"OK":null,"ZERO_RESULT":null,"ERROR":null}},"SortBy":{"__symbolic":"class","members":{},"statics":{"ACCURACY":null,"DISTANCE":null}},"Coords":{"__symbolic":"class","members":{},"statics":{"WGS84":null,"WCONGNAMUL":null,"CONGNAMUL":null,"WTM":null,"TM":null}},"MapTypeId":{"__symbolic":"class","members":{},"statics":{"ROADMAP":null,"SKYVIEW":null,"HYBRID":null,"getCustomMapTypeId":{"__symbolic":"function","parameters":["id"],"value":{"__symbolic":"call","expression":{"__symbolic":"select","expression":{"__symbolic":"reference","name":"KakaoConstants"},"member":"getAPIConstants"},"arguments":["MapTypeId",{"__symbolic":"reference","name":"id"}]}}}},"OverlayMapTypeId":{"__symbolic":"class","members":{},"statics":{"ROADVIEW":null,"OVERLAY":null,"TERRAIN":null,"TRAFFIC":null,"BICYCLE":null,"BICYCLE_HYBRID":null,"USE_DISTRICT":null}},"ControlPosition":{"__symbolic":"class","members":{},"statics":{"TOP":null,"TOPLEFT":null,"TOPRIGHT":null,"LEFT":null,"RIGHT":null,"BOTTOMLEFT":null,"BOTTOM":null,"BOTTOMRIGHT":null}},"CopyrightPosition":{"__symbolic":"class","members":{},"statics":{"BOTTOMLEFT":null,"BOTTOMRIGHT":null}},"MapOptions":{"__symbolic":"interface"},"MarkerOptions":{"__symbolic":"interface"},"MarkerImageOptions":{"__symbolic":"interface"},"InfoWindowOptions":{"__symbolic":"interface"},"CustomOverlayOptions":{"__symbolic":"interface"},"PolylineClassOptions":{"__symbolic":"interface"},"PolylineOptions":{"__symbolic":"interface"},"PolygonClassOptions":{"__symbolic":"interface"},"PolygonOptions":{"__symbolic":"interface"},"CircleClassOptions":{"__symbolic":"interface"},"CircleOptions":{"__symbolic":"interface"},"EllipseClassOptions":{"__symbolic":"interface"},"EllipseOptions":{"__symbolic":"interface"},"RectangleClassOptions":{"__symbolic":"interface"},"RectangleOptions":{"__symbolic":"interface"},"RoadviewOptions":{"__symbolic":"interface"},"StaticMapOptions":{"__symbolic":"interface"},"StaticMapMarkerOptions":{"__symbolic":"interface"},"KeywordSearchOptions":{"__symbolic":"interface"},"AddressSearchOptions":{"__symbolic":"interface"},"Coord2AddressOptions":{"__symbolic":"interface"},"Coord2RegionCodeOptions":{"__symbolic":"interface"},"LevelOptions":{"__symbolic":"interface"},"MarkerClustererOptions":{"__symbolic":"interface"},"DrawingManagerOptions":{"__symbolic":"interface"},"DrawingManagerMarkerOptions":{"__symbolic":"interface"},"DrawingManagerMarkerImageOptions":{"__symbolic":"interface"},"DrawingManagerRectangleOptions":{"__symbolic":"interface"},"DrawingManagerCircleOptions":{"__symbolic":"interface"},"DrawingManagerEllipseOptions":{"__symbolic":"interface"},"DrawingManagerPolylineOptions":{"__symbolic":"interface"},"DrawingManagerArrowOptions":{"__symbolic":"interface"},"DrawingManagerPolygonOptions":{"__symbolic":"interface"},"KakaoEvents":{"__symbolic":"interface"},"KakaoDrawingEvents":{"__symbolic":"interface"},"KakaoStrokeStyles":{"__symbolic":"interface"},"KakaoCategoryCode":{"__symbolic":"interface"},"CustomOverlay":{"__symbolic":"class","members":{"__ctor__":[{"__symbolic":"constructor","parameters":[{"__symbolic":"reference","name":"CustomOverlayOptions"}]}],"setMap":[{"__symbolic":"method"}],"getMap":[{"__symbolic":"method"}],"setPosition":[{"__symbolic":"method"}],"getPosition":[{"__symbolic":"method"}],"setContent":[{"__symbolic":"method"}],"getContent":[{"__symbolic":"method"}],"setZIndex":[{"__symbolic":"method"}],"setVisible":[{"__symbolic":"method"}],"getVisible":[{"__symbolic":"method"}],"getZIndex":[{"__symbolic":"method"}],"setAltitude":[{"__symbolic":"method"}],"getAltitude":[{"__symbolic":"method"}],"setRange":[{"__symbolic":"method"}],"getRange":[{"__symbolic":"method"}]}},"InfoWindow":{"__symbolic":"class","members":{"__ctor__":[{"__symbolic":"constructor","parameters":[{"__symbolic":"reference","name":"InfoWindowOptions"}]}],"open":[{"__symbolic":"method"}],"close":[{"__symbolic":"method"}],"getMap":[{"__symbolic":"method"}],"setPosition":[{"__symbolic":"method"}],"getPosition":[{"__symbolic":"method"}],"setContent":[{"__symbolic":"method"}],"getContent":[{"__symbolic":"method"}],"setZIndex":[{"__symbolic":"method"}],"getZIndex":[{"__symbolic":"method"}],"setAltitude":[{"__symbolic":"method"}],"getAltitude":[{"__symbolic":"method"}],"setRange":[{"__symbolic":"method"}],"getRange":[{"__symbolic":"method"}]}},"KakaoMap":{"__symbolic":"class","members":{"__ctor__":[{"__symbolic":"constructor","parameters":[{"__symbolic":"reference","name":"any"},{"__symbolic":"reference","name":"MapOptions"}]}],"setCenter":[{"__symbolic":"method"}],"getCenter":[{"__symbolic":"method"}],"setLevel":[{"__symbolic":"method"}],"getLevel":[{"__symbolic":"method"}],"setMapTypeId":[{"__symbolic":"method"}],"getMapTypeId":[{"__symbolic":"method"}],"setBounds":[{"__symbolic":"method"}],"getBounds":[{"__symbolic":"method"}],"setMinLevel":[{"__symbolic":"method"}],"setMaxLevel":[{"__symbolic":"method"}],"panBy":[{"__symbolic":"method"}],"panTo":[{"__symbolic":"method"}],"addControl":[{"__symbolic":"method"}],"removeControl":[{"__symbolic":"method"}],"setDraggable":[{"__symbolic":"method"}],"getDraggable":[{"__symbolic":"method"}],"setZoomable":[{"__symbolic":"method"}],"getZoomable":[{"__symbolic":"method"}],"relayout":[{"__symbolic":"method"}],"addOverlayMapTypeId":[{"__symbolic":"method"}],"removeOverlayMapTypeId":[{"__symbolic":"method"}],"setKeyboardShortcuts":[{"__symbolic":"method"}],"getKeyboardShortcuts":[{"__symbolic":"method"}],"setCopyrightPosition":[{"__symbolic":"method"}],"getProjection":[{"__symbolic":"method"}],"setCursor":[{"__symbolic":"method"}]}},"LatLng":{"__symbolic":"class","members":{"__ctor__":[{"__symbolic":"constructor","parameters":[{"__symbolic":"reference","name":"number"},{"__symbolic":"reference","name":"number"}]}],"getLat":[{"__symbolic":"method"}],"getLng":[{"__symbolic":"method"}],"equals":[{"__symbolic":"method"}],"toString":[{"__symbolic":"method"}],"toCoords":[{"__symbolic":"method"}]}},"LatLngBounds":{"__symbolic":"class","members":{"__ctor__":[{"__symbolic":"constructor","parameters":[{"__symbolic":"reference","name":"LatLng"},{"__symbolic":"reference","name":"LatLng"}]}],"getSouthWest":[{"__symbolic":"method"}],"getNorthEast":[{"__symbolic":"method"}],"equals":[{"__symbolic":"method"}],"toString":[{"__symbolic":"method"}],"isEmpty":[{"__symbolic":"method"}],"extend":[{"__symbolic":"method"}],"contain":[{"__symbolic":"method"}]}},"MapTypeControl":{"__symbolic":"class","members":{"__ctor__":[{"__symbolic":"constructor"}]}},"Marker":{"__symbolic":"class","members":{"__ctor__":[{"__symbolic":"constructor","parameters":[{"__symbolic":"reference","name":"MarkerOptions"}]}],"setMap":[{"__symbolic":"method"}],"getMap":[{"__symbolic":"method"}],"setImage":[{"__symbolic":"method"}],"getImage":[{"__symbolic":"method"}],"setPosition":[{"__symbolic":"method"}],"getPosition":[{"__symbolic":"method"}],"setZIndex":[{"__symbolic":"method"}],"getZIndex":[{"__symbolic":"method"}],"setVisible":[{"__symbolic":"method"}],"getVisible":[{"__symbolic":"method"}],"setTitle":[{"__symbolic":"method"}],"getTitle":[{"__symbolic":"method"}],"setDraggable":[{"__symbolic":"method"}],"getDraggable":[{"__symbolic":"method"}],"setClickable":[{"__symbolic":"method"}],"getClickable":[{"__symbolic":"method"}],"setAltitude":[{"__symbolic":"method"}],"getAltitude":[{"__symbolic":"method"}],"setRange":[{"__symbolic":"method"}],"getRange":[{"__symbolic":"method"}],"setOpacity":[{"__symbolic":"method"}],"getOpacity":[{"__symbolic":"method"}]}},"MarkerImage":{"__symbolic":"class","members":{"__ctor__":[{"__symbolic":"constructor","parameters":[{"__symbolic":"reference","name":"string"},{"__symbolic":"reference","name":"Size"},{"__symbolic":"reference","name":"MarkerImageOptions"}]}]}},"Point":{"__symbolic":"class","members":{"__ctor__":[{"__symbolic":"constructor","parameters":[{"__symbolic":"reference","name":"number"},{"__symbolic":"reference","name":"number"}]}],"equals":[{"__symbolic":"method"}],"toString":[{"__symbolic":"method"}]}},"Polygon":{"__symbolic":"class","members":{"__ctor__":[{"__symbolic":"constructor","parameters":[{"__symbolic":"reference","name":"PolygonClassOptions"}]}],"setMap":[{"__symbolic":"method"}],"getMap":[{"__symbolic":"method"}],"setZIndex":[{"__symbolic":"method"}],"getZIndex":[{"__symbolic":"method"}],"setOptions":[{"__symbolic":"method"}],"setPath":[{"__symbolic":"method"}],"getPath":[{"__symbolic":"method"}],"getLength":[{"__symbolic":"method"}],"getArea":[{"__symbolic":"method"}]}},"Polyline":{"__symbolic":"class","members":{"__ctor__":[{"__symbolic":"constructor","parameters":[{"__symbolic":"reference","name":"PolylineClassOptions"}]}],"setMap":[{"__symbolic":"method"}],"getMap":[{"__symbolic":"method"}],"setZIndex":[{"__symbolic":"method"}],"getZIndex":[{"__symbolic":"method"}],"setOptions":[{"__symbolic":"method"}],"setPath":[{"__symbolic":"method"}],"getPath":[{"__symbolic":"method"}],"getLength":[{"__symbolic":"method"}]}},"Rectangle":{"__symbolic":"class","members":{"__ctor__":[{"__symbolic":"constructor","parameters":[{"__symbolic":"reference","name":"RectangleClassOptions"}]}],"setMap":[{"__symbolic":"method"}],"getMap":[{"__symbolic":"method"}],"setZIndex":[{"__symbolic":"method"}],"getZIndex":[{"__symbolic":"method"}],"setOptions":[{"__symbolic":"method"}],"setBounds":[{"__symbolic":"method"}],"getBounds":[{"__symbolic":"method"}]}},"Roadview":{"__symbolic":"class","members":{"__ctor__":[{"__symbolic":"constructor","parameters":[{"__symbolic":"reference","name":"any"},{"__symbolic":"reference","name":"RoadviewOptions"}]}],"setPanoId":[{"__symbolic":"method"}],"getPanoId":[{"__symbolic":"method"}],"setViewpoint":[{"__symbolic":"method"}],"getViewpoint":[{"__symbolic":"method"}],"getViewpointWithPanoId":[{"__symbolic":"method"}],"getPosition":[{"__symbolic":"method"}],"relayout":[{"__symbolic":"method"}]}},"RoadviewClient":{"__symbolic":"class","members":{"__ctor__":[{"__symbolic":"constructor"}],"getNearestPanoId":[{"__symbolic":"method"}]}},"RoadviewOverlay":{"__symbolic":"class","members":{"__ctor__":[{"__symbolic":"constructor"}],"setMap":[{"__symbolic":"method"}],"getMap":[{"__symbolic":"method"}]}},"Size":{"__symbolic":"class","members":{"__ctor__":[{"__symbolic":"constructor","parameters":[{"__symbolic":"reference","name":"number"},{"__symbolic":"reference","name":"number"}]}],"equals":[{"__symbolic":"method"}],"toString":[{"__symbolic":"method"}]}},"StaticMap":{"__symbolic":"class","members":{"__ctor__":[{"__symbolic":"constructor","parameters":[null,{"__symbolic":"reference","name":"StaticMapOptions"}]}],"setCenter":[{"__symbolic":"method"}],"getCenter":[{"__symbolic":"method"}],"setLevel":[{"__symbolic":"method"}],"getLevel":[{"__symbolic":"method"}],"setMapTypeId":[{"__symbolic":"method"}],"getMapTypeId":[{"__symbolic":"method"}]}},"Tileset":{"__symbolic":"class","members":{"__ctor__":[{"__symbolic":"constructor","parameters":[{"__symbolic":"reference","name":"number"},{"__symbolic":"reference","name":"number"},null,{"__symbolic":"reference","name":"Array","arguments":[{"__symbolic":"reference","name":"TilesetCopyright"}]},{"__symbolic":"reference","name":"boolean"},{"__symbolic":"reference","name":"number"},{"__symbolic":"reference","name":"number"}]}],"add":[{"__symbolic":"method"}]}},"TilesetCopyright":{"__symbolic":"class","members":{"__ctor__":[{"__symbolic":"constructor","parameters":[{"__symbolic":"reference","name":"string"},{"__symbolic":"reference","name":"string"},{"__symbolic":"reference","name":"number"}]}]}},"Viewpoint":{"__symbolic":"class","members":{"__ctor__":[{"__symbolic":"constructor","parameters":[{"__symbolic":"reference","name":"number"},{"__symbolic":"reference","name":"number"},{"__symbolic":"reference","name":"number"},{"__symbolic":"reference","name":"number"}]}]}},"ZoomControl":{"__symbolic":"class","members":{"__ctor__":[{"__symbolic":"constructor"}]}},"MarkerClusterer":{"__symbolic":"class","members":{"__ctor__":[{"__symbolic":"constructor","parameters":[{"__symbolic":"reference","name":"MarkerClustererOptions"}]}],"addMarker":[{"__symbolic":"method"}],"addMarkers":[{"__symbolic":"method"}],"removeMarker":[{"__symbolic":"method"}],"removeMarkers":[{"__symbolic":"method"}],"clear":[{"__symbolic":"method"}],"redraw":[{"__symbolic":"method"}],"setGridSize":[{"__symbolic":"method"}],"getGridSize":[{"__symbolic":"method"}],"setMinClusterSize":[{"__symbolic":"method"}],"getMinClusterSize":[{"__symbolic":"method"}],"setAverageCenter":[{"__symbolic":"method"}],"getAverageCenter":[{"__symbolic":"method"}],"setMinLevel":[{"__symbolic":"method"}],"getMinLevel":[{"__symbolic":"method"}],"setTexts":[{"__symbolic":"method"}],"getTexts":[{"__symbolic":"method"}],"setCalculator":[{"__symbolic":"method"}],"getCalculator":[{"__symbolic":"method"}],"setStyles":[{"__symbolic":"method"}],"getStyles":[{"__symbolic":"method"}]}},"KakaoMapsComponent":{"__symbolic":"class","decorators":[{"__symbolic":"call","expression":{"__symbolic":"reference","module":"@angular/core","name":"Component","line":3,"character":1},"arguments":[{"selector":"kakao-maps","template":"<div id=\"kakaomaps-div\" [ngStyle]=\"mapConfig\"></div>","styles":[""]}]}],"members":{"mapConfig":[{"__symbolic":"property","decorators":[{"__symbolic":"call","expression":{"__symbolic":"reference","module":"@angular/core","name":"Input","line":9,"character":3}}]}],"__ctor__":[{"__symbolic":"constructor","parameters":[{"__symbolic":"reference","name":"KakaoMapsProvider"}]}],"ngOnChanges":[{"__symbolic":"method"}],"ngOnInit":[{"__symbolic":"method"}],"ngAfterViewInit":[{"__symbolic":"method"}],"setMapConfig":[{"__symbolic":"method"}],"getMapConfig":[{"__symbolic":"method"}]}},"MapConfig":{"__symbolic":"interface"},"DrawingManager":{"__symbolic":"class","members":{"__ctor__":[{"__symbolic":"constructor","parameters":[{"__symbolic":"reference","name":"DrawingManagerOptions"}]}],"setStyle":[{"__symbolic":"method"}],"setStrokeWeight":[{"__symbolic":"method"}],"setStrokeColor":[{"__symbolic":"method"}],"select":[{"__symbolic":"method"}],"cancel":[{"__symbolic":"method"}],"undo":[{"__symbolic":"method"}],"redo":[{"__symbolic":"method"}],"undoable":[{"__symbolic":"method"}],"redoable":[{"__symbolic":"method"}],"getData":[{"__symbolic":"method"}],"getOverlays":[{"__symbolic":"method"}],"put":[{"__symbolic":"method"}],"remove":[{"__symbolic":"method"}],"addListeners":[{"__symbolic":"method"}],"addListener":[{"__symbolic":"method"}]}},"Toolbox":{"__symbolic":"class","members":{"__ctor__":[{"__symbolic":"constructor","parameters":[{"__symbolic":"error","message":"Expression form not supported","line":7,"character":23,"module":"./src/app/modules/kakao-maps/drawing/kakao-maps.Toolbox"}]}],"getElement":[{"__symbolic":"method"}]}},"Geocoder":{"__symbolic":"class","members":{"__ctor__":[{"__symbolic":"constructor"}],"addressSearch":[{"__symbolic":"method"}],"coord2Address":[{"__symbolic":"method"}],"coord2RegionCode":[{"__symbolic":"method"}],"transCoord":[{"__symbolic":"method"}]}},"Places":{"__symbolic":"class","members":{"__ctor__":[{"__symbolic":"constructor","parameters":[{"__symbolic":"reference","name":"KakaoMap"}]}],"setMap":[{"__symbolic":"method"}],"keywordSearch":[{"__symbolic":"method"}],"categorySearch":[{"__symbolic":"method"}]}},"KakaoMapsProvider":{"__symbolic":"class","decorators":[{"__symbolic":"call","expression":{"__symbolic":"reference","module":"@angular/core","name":"Injectable","line":18,"character":1}}],"members":{"__ctor__":[{"__symbolic":"constructor"}],"loadKakaoMapSDK":[{"__symbolic":"method"}],"init":[{"__symbolic":"method"}],"setContainerStyleConfig":[{"__symbolic":"method"}],"constantInit":[{"__symbolic":"method"}],"safeOp":[{"__symbolic":"method"}],"getMapInstance":[{"__symbolic":"method"}],"addListeners":[{"__symbolic":"method"}],"addListener":[{"__symbolic":"method"}],"removeListeners":[{"__symbolic":"method"}],"removeListener":[{"__symbolic":"method"}],"trigger":[{"__symbolic":"method"}],"preventMap":[{"__symbolic":"method"}],"disableHD":[{"__symbolic":"method"}],"ngOnInit":[{"__symbolic":"method"}]}}},"origins":{"KakaoMapsModule":"./src/app/modules/kakao-maps/kakao-maps.module","AbstractOverlay":"./src/app/modules/kakao-maps/basic/kakao-maps.AbstractOverlay","Circle":"./src/app/modules/kakao-maps/basic/kakao-maps.Circle","KakaoConstants":"./src/app/modules/kakao-maps/basic/kakao-maps.constants","OverlayType":"./src/app/modules/kakao-maps/basic/kakao-maps.constants","Status":"./src/app/modules/kakao-maps/basic/kakao-maps.constants","SortBy":"./src/app/modules/kakao-maps/basic/kakao-maps.constants","Coords":"./src/app/modules/kakao-maps/basic/kakao-maps.constants","MapTypeId":"./src/app/modules/kakao-maps/basic/kakao-maps.constants","OverlayMapTypeId":"./src/app/modules/kakao-maps/basic/kakao-maps.constants","ControlPosition":"./src/app/modules/kakao-maps/basic/kakao-maps.constants","CopyrightPosition":"./src/app/modules/kakao-maps/basic/kakao-maps.constants","MapOptions":"./src/app/modules/kakao-maps/basic/kakao-maps.constants","MarkerOptions":"./src/app/modules/kakao-maps/basic/kakao-maps.constants","MarkerImageOptions":"./src/app/modules/kakao-maps/basic/kakao-maps.constants","InfoWindowOptions":"./src/app/modules/kakao-maps/basic/kakao-maps.constants","CustomOverlayOptions":"./src/app/modules/kakao-maps/basic/kakao-maps.constants","PolylineClassOptions":"./src/app/modules/kakao-maps/basic/kakao-maps.constants","PolylineOptions":"./src/app/modules/kakao-maps/basic/kakao-maps.constants","PolygonClassOptions":"./src/app/modules/kakao-maps/basic/kakao-maps.constants","PolygonOptions":"./src/app/modules/kakao-maps/basic/kakao-maps.constants","CircleClassOptions":"./src/app/modules/kakao-maps/basic/kakao-maps.constants","CircleOptions":"./src/app/modules/kakao-maps/basic/kakao-maps.constants","EllipseClassOptions":"./src/app/modules/kakao-maps/basic/kakao-maps.constants","EllipseOptions":"./src/app/modules/kakao-maps/basic/kakao-maps.constants","RectangleClassOptions":"./src/app/modules/kakao-maps/basic/kakao-maps.constants","RectangleOptions":"./src/app/modules/kakao-maps/basic/kakao-maps.constants","RoadviewOptions":"./src/app/modules/kakao-maps/basic/kakao-maps.constants","StaticMapOptions":"./src/app/modules/kakao-maps/basic/kakao-maps.constants","StaticMapMarkerOptions":"./src/app/modules/kakao-maps/basic/kakao-maps.constants","KeywordSearchOptions":"./src/app/modules/kakao-maps/basic/kakao-maps.constants","AddressSearchOptions":"./src/app/modules/kakao-maps/basic/kakao-maps.constants","Coord2AddressOptions":"./src/app/modules/kakao-maps/basic/kakao-maps.constants","Coord2RegionCodeOptions":"./src/app/modules/kakao-maps/basic/kakao-maps.constants","LevelOptions":"./src/app/modules/kakao-maps/basic/kakao-maps.constants","MarkerClustererOptions":"./src/app/modules/kakao-maps/basic/kakao-maps.constants","DrawingManagerOptions":"./src/app/modules/kakao-maps/basic/kakao-maps.constants","DrawingManagerMarkerOptions":"./src/app/modules/kakao-maps/basic/kakao-maps.constants","DrawingManagerMarkerImageOptions":"./src/app/modules/kakao-maps/basic/kakao-maps.constants","DrawingManagerRectangleOptions":"./src/app/modules/kakao-maps/basic/kakao-maps.constants","DrawingManagerCircleOptions":"./src/app/modules/kakao-maps/basic/kakao-maps.constants","DrawingManagerEllipseOptions":"./src/app/modules/kakao-maps/basic/kakao-maps.constants","DrawingManagerPolylineOptions":"./src/app/modules/kakao-maps/basic/kakao-maps.constants","DrawingManagerArrowOptions":"./src/app/modules/kakao-maps/basic/kakao-maps.constants","DrawingManagerPolygonOptions":"./src/app/modules/kakao-maps/basic/kakao-maps.constants","KakaoEvents":"./src/app/modules/kakao-maps/basic/kakao-maps.constants","KakaoDrawingEvents":"./src/app/modules/kakao-maps/basic/kakao-maps.constants","KakaoStrokeStyles":"./src/app/modules/kakao-maps/basic/kakao-maps.constants","KakaoCategoryCode":"./src/app/modules/kakao-maps/basic/kakao-maps.constants","CustomOverlay":"./src/app/modules/kakao-maps/basic/kakao-maps.CustomOverlay","InfoWindow":"./src/app/modules/kakao-maps/basic/kakao-maps.InfoWindow","KakaoMap":"./src/app/modules/kakao-maps/basic/kakao-maps.KakaoMap","LatLng":"./src/app/modules/kakao-maps/basic/kakao-maps.LatLng","LatLngBounds":"./src/app/modules/kakao-maps/basic/kakao-maps.LatLngBounds","MapTypeControl":"./src/app/modules/kakao-maps/basic/kakao-maps.MapTypeControl","Marker":"./src/app/modules/kakao-maps/basic/kakao-maps.Marker","MarkerImage":"./src/app/modules/kakao-maps/basic/kakao-maps.MarkerImage","Point":"./src/app/modules/kakao-maps/basic/kakao-maps.Point","Polygon":"./src/app/modules/kakao-maps/basic/kakao-maps.Polygon","Polyline":"./src/app/modules/kakao-maps/basic/kakao-maps.Polyline","Rectangle":"./src/app/modules/kakao-maps/basic/kakao-maps.Rectangle","Roadview":"./src/app/modules/kakao-maps/basic/kakao-maps.Roadview","RoadviewClient":"./src/app/modules/kakao-maps/basic/kakao-maps.RoadviewClient","RoadviewOverlay":"./src/app/modules/kakao-maps/basic/kakao-maps.RoadviewOverlay","Size":"./src/app/modules/kakao-maps/basic/kakao-maps.Size","StaticMap":"./src/app/modules/kakao-maps/basic/kakao-maps.StaticMap","Tileset":"./src/app/modules/kakao-maps/basic/kakao-maps.Tileset","TilesetCopyright":"./src/app/modules/kakao-maps/basic/kakao-maps.TilesetCopyright","Viewpoint":"./src/app/modules/kakao-maps/basic/kakao-maps.Viewpoint","ZoomControl":"./src/app/modules/kakao-maps/basic/kakao-maps.ZoomControl","MarkerClusterer":"./src/app/modules/kakao-maps/clusters/kakao-maps.MarkerClusterer","KakaoMapsComponent":"./src/app/modules/kakao-maps/components/kakao-maps.component","MapConfig":"./src/app/modules/kakao-maps/components/kakao-maps.component","DrawingManager":"./src/app/modules/kakao-maps/drawing/kakao-maps.DrawingManager","Toolbox":"./src/app/modules/kakao-maps/drawing/kakao-maps.Toolbox","Geocoder":"./src/app/modules/kakao-maps/services/kakao-maps.Geocoder","Places":"./src/app/modules/kakao-maps/services/kakao-maps.Places","KakaoMapsProvider":"./src/app/modules/kakao-maps/kakao-maps.provider"},"importAs":"kakao-maps-sdk"}